ih/__init__.py
ih/_version.py
ih/chart.py
ih/cli.py
ih/helpers.py
ih/palette.py
ih/palettes/alpaca.txt
ih/palettes/floss-dmc.txt
ih/palettes/floss-pdx.txt
ih/palettes/floss.txt
ih/palettes/lego.txt
ih/palettes/newlego.txt
ih/palettes/perler.txt
ih/palettes/wool.txt
ih/styling/floss.png
ih/styling/lego.png
ih/styling/perler.png
ih/styling/styling.css
ih/styling/styling.html
ih/styling/wool.png
ih-0.6.0.dist-info/LICENSE
ih-0.6.0.dist-info/METADATA
ih-0.6.0.dist-info/WHEEL
ih-0.6.0.dist-info/entry_points.txt
ih-0.6.0.dist-info/top_level.txt
ih-0.6.0.dist-info/RECORD
