Metadata-Version: 2.1
Name: ih
Version: 0.6.0
Summary: A very persuasive package, for creating embroidery patterns
Home-page: https://github.com/glasnt/ih
Author: Katie McLaughlin
Author-email: katie@glasnt.com
License: UNKNOWN
Platform: UNKNOWN
Classifier: Programming Language :: Python :: 3
Classifier: License :: OSI Approved :: BSD License
Requires-Dist: click
Requires-Dist: pillow
Requires-Dist: scipy
Requires-Dist: tabulate
